"prediction_btc/Model_F_2,4_Acc97.h5"
"prediction_btc/Model_T_2,4_Acc97.pkl"
prediction_btc/__init__.py
prediction_btc/package.py
prediction_btc-0.0.1.dist-info/LICENCE
prediction_btc-0.0.1.dist-info/METADATA
prediction_btc-0.0.1.dist-info/WHEEL
prediction_btc-0.0.1.dist-info/top_level.txt
prediction_btc-0.0.1.dist-info/RECORD
