Metadata-Version: 2.2
Name: prediction_btc
Version: 0.0.1
Summary: A small example package
Author-email: Komang Nitay Prasaddas <nitay06@students.amikom.ac.id>
Project-URL: Homepage, https://github.com/pypa/sampleproject
Project-URL: Issues, https://github.com/pypa/sampleproject/issues
Keywords: prediction,bitcoin,ai
Classifier: Programming Language :: Python :: 3
Classifier: License :: OSI Approved :: MIT License
Classifier: Operating System :: OS Independent
Requires-Python: >=3.8
License-File: LICENCE
Requires-Dist: opencv-contrib-python
